safenax/__init__.py
safenax/fragile_ant.py
safenax/eco_ant/__init__.py
safenax/eco_ant/eco_ant_v1.py
safenax/eco_ant/eco_ant_v2.py
safenax/frozen_lake/__init__.py
safenax/frozen_lake/frozen_lake_v1.py
safenax/frozen_lake/frozen_lake_v2.py
safenax/portfolio_optimization/__init__.py
safenax/portfolio_optimization/po_crypto.py
safenax/portfolio_optimization/po_garch.py
safenax/wrappers/__init__.py
safenax/wrappers/brax.py
safenax/wrappers/log.py
safenax-0.4.6.dist-info/METADATA
safenax-0.4.6.dist-info/WHEEL
safenax-0.4.6.dist-info/licenses/LICENSE
safenax-0.4.6.dist-info/RECORD
