Metadata-Version: 2.4
Name: safenax
Version: 0.4.6
Summary: Constrained environments with a gymnax interface
Project-URL: Homepage, https://github.com/0xprofessooor/safenax
Project-URL: Repository, https://github.com/0xprofessooor/safenax
Project-URL: Issues, https://github.com/0xprofessooor/safenax/issues
Author: 0xprofessooor
License: MIT
License-File: LICENSE
Keywords: environments,gymnax,jax,portfolio-optimization,reinforcement-learning
Classifier: Development Status :: 3 - Alpha
Classifier: Intended Audience :: Developers
Classifier: Intended Audience :: Science/Research
Classifier: License :: OSI Approved :: MIT License
Classifier: Programming Language :: Python :: 3
Classifier: Programming Language :: Python :: 3.11
Classifier: Programming Language :: Python :: 3.12
Classifier: Topic :: Scientific/Engineering :: Artificial Intelligence
Requires-Python: >=3.11
Requires-Dist: brax>=0.13.0
Requires-Dist: chex>=0.1.91
Requires-Dist: flax>=0.12.1
Requires-Dist: gymnax>=0.0.9
Requires-Dist: jax>=0.8.1
Requires-Dist: matplotlib>=3.10.7
Requires-Dist: polars>=1.35.2
